tiima/__init__.py
tiima/settings.py
tiima/tiima.py
tiima-0.1.0.dist-info/LICENSE
tiima-0.1.0.dist-info/WHEEL
tiima-0.1.0.dist-info/METADATA
tiima-0.1.0.dist-info/RECORD
