Metadata-Version: 2.1
Name: tiima
Version: 0.1.0
Summary: Python API Client for Visma Tiima
Home-page: https://gitlab.com/python-poetry/poetry
License: MIT
Author: Frank Wickström
Author-email: no-email@example.com
Requires-Python: >=3.6,<4.0
Classifier: License :: OSI Approved :: MIT License
Classifier: Programming Language :: Python :: 3
Classifier: Programming Language :: Python :: 3.6
Classifier: Programming Language :: Python :: 3.7
Requires-Dist: beautifulsoup4 (>=4.8,<5.0)
Requires-Dist: environs (>=7.2,<8.0)
Requires-Dist: requests (>=2.23,<3.0)
Project-URL: Repository, https://gitlab.com/python-poetry/poetry
